aiomonitor/__init__.py
aiomonitor/cli.py
aiomonitor/console.py
aiomonitor/monitor.py
aiomonitor/mypy_types.py
aiomonitor/task.py
aiomonitor/telnet.py
aiomonitor/types.py
aiomonitor/utils.py
aiomonitor_ng-0.7.2.dist-info/LICENSE
aiomonitor_ng-0.7.2.dist-info/METADATA
aiomonitor_ng-0.7.2.dist-info/WHEEL
aiomonitor_ng-0.7.2.dist-info/top_level.txt
aiomonitor_ng-0.7.2.dist-info/RECORD
