Metadata-Version: 2.1
Name: aiomonitor-ng
Version: 0.7.2
Summary: aiomonitor-ng adds monitor and python REPL capabilities for asyncio application
Home-page: https://github.com/achimnol/aiomonitor-ng
Download-URL: https://pypi.python.org/pypi/aiomonitor-ng
Author: Nikolay Novik
Author-email: nickolainovik@gmail.com
License: Apache 2
Platform: POSIX
Classifier: License :: OSI Approved :: MIT License
Classifier: Intended Audience :: Developers
Classifier: Programming Language :: Python :: 3
Classifier: Programming Language :: Python :: 3.8
Classifier: Programming Language :: Python :: 3.9
Classifier: Programming Language :: Python :: 3.10
Classifier: Operating System :: POSIX
Classifier: Development Status :: 3 - Alpha
Classifier: Framework :: AsyncIO
License-File: LICENSE
Requires-Dist: attrs (>=20)
Requires-Dist: click (>=8)
Requires-Dist: janus (>=1.0)
Requires-Dist: terminaltables
Requires-Dist: typing-extensions (>=4.1)
Requires-Dist: prompt-toolkit (>=3.0)
Requires-Dist: aioconsole
